rest_witchcraft/__init__.py
rest_witchcraft/__version__.py
rest_witchcraft/field_mapping.py
rest_witchcraft/fields.py
rest_witchcraft/filters.py
rest_witchcraft/generics.py
rest_witchcraft/mixins.py
rest_witchcraft/routers.py
rest_witchcraft/serializers.py
rest_witchcraft/utils.py
rest_witchcraft/viewsets.py
django_rest_witchcraft-0.12.1.dist-info/LICENSE
django_rest_witchcraft-0.12.1.dist-info/METADATA
django_rest_witchcraft-0.12.1.dist-info/WHEEL
django_rest_witchcraft-0.12.1.dist-info/top_level.txt
django_rest_witchcraft-0.12.1.dist-info/RECORD
